pythonthegathering/__init__.py
pythonthegathering/mana_pool.py
pythonthegathering/spell.py
pythonthegathering-1.2.1.dist-info/DESCRIPTION.rst
pythonthegathering-1.2.1.dist-info/METADATA
pythonthegathering-1.2.1.dist-info/RECORD
pythonthegathering-1.2.1.dist-info/WHEEL
pythonthegathering-1.2.1.dist-info/metadata.json
pythonthegathering-1.2.1.dist-info/top_level.txt
