Metadata-Version: 2.0
Name: pythonthegathering
Version: 1.2.1
Summary: Replaces everything good and practical about Python with MTG!
Home-page: https://github.com/linky00/pythonthegathering
Author: Theo Hamilton/linky00
Author-email: linky00@plotholestudios.com
License: MIT
Download-URL: https://github.com/linky00/pythonthegathering/archive/v1.2.tar.gz
Keywords: decorators mtg
Platform: UNKNOWN
Classifier: Development Status :: 3 - Alpha
Classifier: Programming Language :: Python :: 3.3
Classifier: Programming Language :: Python :: 3.4
Classifier: Programming Language :: Python :: 3.5
Classifier: Programming Language :: Python :: 3.6
